py_template_creator/__init__.py
py_template_creator/main.py
py_template_creator/api-scelet/cookiecutter.json
py_template_creator/api-scelet/{{ cookiecutter.project_name }}/.docker.env
py_template_creator/api-scelet/{{ cookiecutter.project_name }}/.dockerignore
py_template_creator/api-scelet/{{ cookiecutter.project_name }}/.env
py_template_creator/api-scelet/{{ cookiecutter.project_name }}/.env.example
py_template_creator/api-scelet/{{ cookiecutter.project_name }}/.gitignore
py_template_creator/api-scelet/{{ cookiecutter.project_name }}/.pre-commit-config.yaml
py_template_creator/api-scelet/{{ cookiecutter.project_name }}/docker-compose.yaml
py_template_creator/api-scelet/{{ cookiecutter.project_name }}/rest_api/Dockerfile
py_template_creator/api-scelet/{{ cookiecutter.project_name }}/rest_api/Makefile
py_template_creator/api-scelet/{{ cookiecutter.project_name }}/rest_api/README.md
py_template_creator/api-scelet/{{ cookiecutter.project_name }}/rest_api/pyproject.toml
py_template_creator/api-scelet/{{ cookiecutter.project_name }}/rest_api/assets/.gitkeep
py_template_creator/api-scelet/{{ cookiecutter.project_name }}/rest_api/config/migrate.sh
py_template_creator/api-scelet/{{ cookiecutter.project_name }}/rest_api/config/run.sh
py_template_creator/api-scelet/{{ cookiecutter.project_name }}/rest_api/config/test.sh
py_template_creator/api-scelet/{{ cookiecutter.project_name }}/rest_api/package/__init__.py
py_template_creator/api-scelet/{{ cookiecutter.project_name }}/rest_api/package/alembic.ini
py_template_creator/api-scelet/{{ cookiecutter.project_name }}/rest_api/package/app/__init__.py
py_template_creator/api-scelet/{{ cookiecutter.project_name }}/rest_api/package/app/main.py
py_template_creator/api-scelet/{{ cookiecutter.project_name }}/rest_api/package/app/settings.py
py_template_creator/api-scelet/{{ cookiecutter.project_name }}/rest_api/package/app/shell.py
py_template_creator/api-scelet/{{ cookiecutter.project_name }}/rest_api/package/app/sync_assets.py
py_template_creator-3.1.0.dist-info/entry_points.txt
py_template_creator-3.1.0.dist-info/LICENSE
py_template_creator-3.1.0.dist-info/WHEEL
py_template_creator-3.1.0.dist-info/METADATA
py_template_creator-3.1.0.dist-info/RECORD
