Metadata-Version: 2.1
Name: py_template_creator
Version: 3.1.0
Summary: Generate your python project template with ease.
Author-email: Ivan Djuraki <ivan.djuraki@bridgewaterlabs.com>
Classifier: License :: OSI Approved :: Apache Software License
Requires-Dist: cookiecutter
